{"ID": "25-9021", "TITLE": "Farm and Home Management Educators", "MEDIAN SALARY 2024": 58120.0, "TOTAL EMPLOYMENT": 10260.0, "EMPLOYMENT PERCENT CHANGE": -2.5, "OBSERVED AI EXPOSURE": 0.0, "PSS": 0.2366122007369995, "PPG": 0.2293332815170288, "EXPERTISE PERCENTILE": 71.88275146484375, "REQUIRED SKILLS": [{"O*NET-SOC Code": "25-9021", "Element Name": "Installation", "Data Value": 0.0}, {"O*NET-SOC Code": "25-9021", "Element Name": "Equipment Selection", "Data Value": 0.25}, {"O*NET-SOC Code": "25-9021", "Element Name": "Technology Design", "Data Value": 1.5}, {"O*NET-SOC Code": "25-9021", "Element Name": "Operations Analysis", "Data Value": 2.5}, {"O*NET-SOC Code": "25-9021", "Element Name": "Complex Problem Solving", "Data Value": 4.0}, {"O*NET-SOC Code": "25-9021", "Element Name": "Service Orientation", "Data Value": 3.88}, {"O*NET-SOC Code": "25-9021", "Element Name": "Instructing", "Data Value": 3.88}, {"O*NET-SOC Code": "25-9021", "Element Name": "Negotiation", "Data Value": 3.25}, {"O*NET-SOC Code": "25-9021", "Element Name": "Persuasion", "Data Value": 3.88}, {"O*NET-SOC Code": "25-9021", "Element Name": "Coordination", "Data Value": 3.88}, {"O*NET-SOC Code": "25-9021", "Element Name": "Social Perceptiveness", "Data Value": 4.0}, {"O*NET-SOC Code": "25-9021", "Element Name": "Monitoring", "Data Value": 4.0}, {"O*NET-SOC Code": "25-9021", "Element Name": "Programming", "Data Value": 1.62}, {"O*NET-SOC Code": "25-9021", "Element Name": "Operations Monitoring", "Data Value": 2.25}, {"O*NET-SOC Code": "25-9021", "Element Name": "Systems Analysis", "Data Value": 3.62}, {"O*NET-SOC Code": "25-9021", "Element Name": "Management of Personnel Resources", "Data Value": 2.88}, {"O*NET-SOC Code": "25-9021", "Element Name": "Management of Material Resources", "Data Value": 2.5}, {"O*NET-SOC Code": "25-9021", "Element Name": "Management of Financial Resources", "Data Value": 2.75}, {"O*NET-SOC Code": "25-9021", "Element Name": "Time Management", "Data Value": 3.25}, {"O*NET-SOC Code": "25-9021", "Element Name": "Systems Evaluation", "Data Value": 4.0}, {"O*NET-SOC Code": "25-9021", "Element Name": "Judgment and Decision Making", "Data Value": 4.0}, {"O*NET-SOC Code": "25-9021", "Element Name": "Quality Control Analysis", "Data Value": 1.25}, {"O*NET-SOC Code": "25-9021", "Element Name": "Repairing", "Data Value": 0.0}, {"O*NET-SOC Code": "25-9021", "Element Name": "Troubleshooting", "Data Value": 0.5}, {"O*NET-SOC Code": "25-9021", "Element Name": "Equipment Maintenance", "Data Value": 0.0}, {"O*NET-SOC Code": "25-9021", "Element Name": "Operation and Control", "Data Value": 2.25}, {"O*NET-SOC Code": "25-9021", "Element Name": "Learning Strategies", "Data Value": 4.12}, {"O*NET-SOC Code": "25-9021", "Element Name": "Active Learning", "Data Value": 4.5}, {"O*NET-SOC Code": "25-9021", "Element Name": "Writing", "Data Value": 3.88}, {"O*NET-SOC Code": "25-9021", "Element Name": "Critical Thinking", "Data Value": 3.88}, {"O*NET-SOC Code": "25-9021", "Element Name": "Science", "Data Value": 2.75}, {"O*NET-SOC Code": "25-9021", "Element Name": "Mathematics", "Data Value": 3.5}, {"O*NET-SOC Code": "25-9021", "Element Name": "Speaking", "Data Value": 4.25}, {"O*NET-SOC Code": "25-9021", "Element Name": "Active Listening", "Data Value": 4.12}, {"O*NET-SOC Code": "25-9021", "Element Name": "Reading Comprehension", "Data Value": 4.75}], "ASSOCIATED TASKS": [{"ONETSOCCode": "25-9021", "Task": "Prepare and distribute leaflets, pamphlets, and visual aids for educational and informational purposes.", "TaskType": "Core", "task_importance_score": 3.69, "penetration": 0.0}, {"ONETSOCCode": "25-9021", "Task": "Maintain records of services provided and the effects of advice given.", "TaskType": "Core", "task_importance_score": 3.88, "penetration": 0.0}, {"ONETSOCCode": "25-9021", "Task": "Organize, advise, and participate in community activities and organizations, such as county and state fair events and 4-H Clubs.", "TaskType": "Core", "task_importance_score": 3.64, "penetration": 0.0}, {"ONETSOCCode": "25-9021", "Task": "Schedule and make regular visits to farmers.", "TaskType": "Core", "task_importance_score": 3.64, "penetration": 0.0}, {"ONETSOCCode": "25-9021", "Task": "Research information requested by farmers.", "TaskType": "Core", "task_importance_score": 4.08, "penetration": 0.0}, {"ONETSOCCode": "25-9021", "Task": "Provide direct assistance to farmers by performing activities such as purchasing or selling products and supplies, supervising properties, and collecting soil and herbage samples for testing.", "TaskType": "Supplemental", "task_importance_score": 2.95, "penetration": 0.0}, {"ONETSOCCode": "25-9021", "Task": "Collaborate with social service and health care professionals to advise individuals and families on home management practices, such as budget planning, meal preparation, and time management.", "TaskType": "Supplemental", "task_importance_score": 3.2, "penetration": 0.0}, {"ONETSOCCode": "25-9021", "Task": "Set and monitor production targets.", "TaskType": "Supplemental", "task_importance_score": 3.21, "penetration": 0.0}, {"ONETSOCCode": "25-9021", "Task": "Advise farmers and demonstrate techniques in areas such as feeding and health maintenance of livestock, growing and harvesting practices, and financial planning.", "TaskType": "Core", "task_importance_score": 4.28, "penetration": 0.0}, {"ONETSOCCode": "25-9021", "Task": "Collect and evaluate data to determine community program needs.", "TaskType": "Core", "task_importance_score": 4.04, "penetration": 0.0}, {"ONETSOCCode": "25-9021", "Task": "Conduct agricultural research, analyze data, and prepare research reports.", "TaskType": "Core", "task_importance_score": 3.6, "penetration": 0.0}, {"ONETSOCCode": "25-9021", "Task": "Conduct field demonstrations of new products, techniques, or services.", "TaskType": "Core", "task_importance_score": 3.88, "penetration": 0.0}, {"ONETSOCCode": "25-9021", "Task": "Act as an advocate for farmers or farmers' groups.", "TaskType": "Core", "task_importance_score": 4.0, "penetration": 0.0}, {"ONETSOCCode": "25-9021", "Task": "Collaborate with producers to diagnose and prevent management and production problems.", "TaskType": "Core", "task_importance_score": 4.24, "penetration": 0.0}, {"ONETSOCCode": "25-9021", "Task": "Conduct classes or deliver lectures on subjects such as nutrition, home management, and farming techniques.", "TaskType": "Core", "task_importance_score": 4.27, "penetration": 0.0}], "RELATED OCCUPATIONS": [{"O*NET-SOC Code": "25-9021", "Related O*NET-SOC Code": "25-1041", "Relatedness Tier": "Primary-Short"}, {"O*NET-SOC Code": "25-9021", "Related O*NET-SOC Code": "13-1111", "Relatedness Tier": "Primary-Short"}, {"O*NET-SOC Code": "25-9021", "Related O*NET-SOC Code": "19-1031", "Relatedness Tier": "Primary-Short"}, {"O*NET-SOC Code": "25-9021", "Related O*NET-SOC Code": "19-1013", "Relatedness Tier": "Primary-Short"}, {"O*NET-SOC Code": "25-9021", "Related O*NET-SOC Code": "25-1194", "Relatedness Tier": "Primary-Short"}, {"O*NET-SOC Code": "25-9021", "Related O*NET-SOC Code": "25-1011", "Relatedness Tier": "Primary-Long"}, {"O*NET-SOC Code": "25-9021", "Related O*NET-SOC Code": "25-2023", "Relatedness Tier": "Primary-Long"}, {"O*NET-SOC Code": "25-9021", "Related O*NET-SOC Code": "25-2032", "Relatedness Tier": "Primary-Long"}, {"O*NET-SOC Code": "25-9021", "Related O*NET-SOC Code": "21-1091", "Relatedness Tier": "Primary-Long"}, {"O*NET-SOC Code": "25-9021", "Related O*NET-SOC Code": "25-9031", "Relatedness Tier": "Primary-Long"}, {"O*NET-SOC Code": "25-9021", "Related O*NET-SOC Code": "41-3091", "Relatedness Tier": "Supplemental"}, {"O*NET-SOC Code": "25-9021", "Related O*NET-SOC Code": "45-1011", "Relatedness Tier": "Supplemental"}, {"O*NET-SOC Code": "25-9021", "Related O*NET-SOC Code": "45-2011", "Relatedness Tier": "Supplemental"}, {"O*NET-SOC Code": "25-9021", "Related O*NET-SOC Code": "21-1094", "Relatedness Tier": "Supplemental"}, {"O*NET-SOC Code": "25-9021", "Related O*NET-SOC Code": "11-9013", "Relatedness Tier": "Supplemental"}, {"O*NET-SOC Code": "25-9021", "Related O*NET-SOC Code": "17-2021", "Relatedness Tier": "Supplemental"}, {"O*NET-SOC Code": "25-9021", "Related O*NET-SOC Code": "19-1031", "Relatedness Tier": "Supplemental"}, {"O*NET-SOC Code": "25-9021", "Related O*NET-SOC Code": "19-4071", "Relatedness Tier": "Supplemental"}, {"O*NET-SOC Code": "25-9021", "Related O*NET-SOC Code": "19-1032", "Relatedness Tier": "Supplemental"}, {"O*NET-SOC Code": "25-9021", "Related O*NET-SOC Code": "11-1011", "Relatedness Tier": "Supplemental"}], "TECH SKILLS": [{"O*NET-SOC Code": "25-9021", "Example": "Adobe Experience Manager (AEM)"}, {"O*NET-SOC Code": "25-9021", "Example": "ESRI ArcGIS software"}, {"O*NET-SOC Code": "25-9021", "Example": "Geographic information system GIS software"}, {"O*NET-SOC Code": "25-9021", "Example": "Image editing software"}, {"O*NET-SOC Code": "25-9021", "Example": "Kahoot!"}, {"O*NET-SOC Code": "25-9021", "Example": "Microsoft Dynamics"}, {"O*NET-SOC Code": "25-9021", "Example": "Microsoft Excel"}, {"O*NET-SOC Code": "25-9021", "Example": "Microsoft Internet Explorer"}, {"O*NET-SOC Code": "25-9021", "Example": "Microsoft Office software"}, {"O*NET-SOC Code": "25-9021", "Example": "Microsoft Outlook"}, {"O*NET-SOC Code": "25-9021", "Example": "Microsoft PowerPoint"}, {"O*NET-SOC Code": "25-9021", "Example": "Microsoft SharePoint"}, {"O*NET-SOC Code": "25-9021", "Example": "Microsoft Word"}, {"O*NET-SOC Code": "25-9021", "Example": "Order management software"}, {"O*NET-SOC Code": "25-9021", "Example": "SAP software"}, {"O*NET-SOC Code": "25-9021", "Example": "ServiceNow"}, {"O*NET-SOC Code": "25-9021", "Example": "Web browser software"}]}